{
  "stock_id": "6949",
  "price_mode": "adjusted",
  "data_through": "2026-06-30",
  "rows": [
    {
      "date": "2024-05-08",
      "open": 164.165511,
      "high": 170.593679,
      "low": 162.187614,
      "close": 164.165511,
      "volume": 28000.0
    },
    {
      "date": "2024-05-09",
      "open": 164.165511,
      "high": 164.165511,
      "low": 160.209716,
      "close": 162.187614,
      "volume": 21403.0
    },
    {
      "date": "2024-05-10",
      "open": 162.187614,
      "high": 162.187614,
      "low": 157.242869,
      "close": 157.242869,
      "volume": 49000.0
    },
    {
      "date": "2024-05-13",
      "open": 155.264972,
      "high": 155.264972,
      "low": 141.914162,
      "close": 147.353381,
      "volume": 119000.0
    },
    {
      "date": "2024-05-14",
      "open": 152.792599,
      "high": 152.792599,
      "low": 145.869957,
      "close": 145.869957,
      "volume": 8000.0
    },
    {
      "date": "2024-05-15",
      "open": 145.869957,
      "high": 151.309176,
      "low": 142.408636,
      "close": 146.858906,
      "volume": 32000.0
    },
    {
      "date": "2024-05-16",
      "open": 147.353381,
      "high": 148.34233,
      "low": 144.386534,
      "close": 148.34233,
      "volume": 38000.0
    },
    {
      "date": "2024-05-17",
      "open": 148.34233,
      "high": 148.34233,
      "low": 145.375483,
      "close": 146.364432,
      "volume": 22000.0
    },
    {
      "date": "2024-05-20",
      "open": 147.353381,
      "high": 158.726293,
      "low": 146.858906,
      "close": 149.331278,
      "volume": 41000.0
    },
    {
      "date": "2024-05-21",
      "open": 148.34233,
      "high": 148.34233,
      "low": 141.914162,
      "close": 146.364432,
      "volume": 72000.0
    },
    {
      "date": "2024-05-22",
      "open": 145.375483,
      "high": 145.375483,
      "low": 143.397585,
      "close": 145.375483,
      "volume": 33000.0
    },
    {
      "date": "2024-05-23",
      "open": 144.386534,
      "high": 144.386534,
      "low": 136.474943,
      "close": 141.914162,
      "volume": 70000.0
    },
    {
      "date": "2024-05-24",
      "open": 140.925213,
      "high": 140.925213,
      "low": 136.474943,
      "close": 138.947315,
      "volume": 38000.0
    },
    {
      "date": "2024-05-27",
      "open": 148.836804,
      "high": 148.836804,
      "low": 137.463892,
      "close": 137.958366,
      "volume": 28000.0
    },
    {
      "date": "2024-05-28",
      "open": 137.463892,
      "high": 137.958366,
      "low": 134.497045,
      "close": 134.497045,
      "volume": 44033.0
    },
    {
      "date": "2024-05-29",
      "open": 133.508097,
      "high": 139.44179,
      "low": 131.530199,
      "close": 139.44179,
      "volume": 44000.0
    },
    {
      "date": "2024-05-30",
      "open": 136.969418,
      "high": 136.969418,
      "low": 132.024673,
      "close": 132.519148,
      "volume": 29000.0
    },
    {
      "date": "2024-05-31",
      "open": 129.552301,
      "high": 132.519148,
      "low": 128.563352,
      "close": 129.057827,
      "volume": 35000.0
    },
    {
      "date": "2024-06-03",
      "open": 132.024673,
      "high": 132.024673,
      "low": 129.552301,
      "close": 129.552301,
      "volume": 30000.0
    },
    {
      "date": "2024-06-04",
      "open": 129.552301,
      "high": 129.552301,
      "low": 127.079929,
      "close": 128.563352,
      "volume": 23210.0
    },
    {
      "date": "2024-06-05",
      "open": 129.057827,
      "high": 130.54125,
      "low": 128.563352,
      "close": 130.54125,
      "volume": 32000.0
    },
    {
      "date": "2024-06-06",
      "open": 131.035724,
      "high": 131.530199,
      "low": 130.54125,
      "close": 131.530199,
      "volume": 32000.0
    },
    {
      "date": "2024-06-07",
      "open": 133.508097,
      "high": 133.508097,
      "low": 129.552301,
      "close": 129.552301,
      "volume": 30000.0
    },
    {
      "date": "2024-06-11",
      "open": 129.057827,
      "high": 129.057827,
      "low": 119.662813,
      "close": 127.079929,
      "volume": 129000.0
    },
    {
      "date": "2024-06-12",
      "open": 123.618608,
      "high": 128.563352,
      "low": 122.629659,
      "close": 124.607557,
      "volume": 52000.0
    },
    {
      "date": "2024-06-13",
      "open": 124.113082,
      "high": 128.563352,
      "low": 124.113082,
      "close": 125.102031,
      "volume": 29000.0
    },
    {
      "date": "2024-06-14",
      "open": 125.102031,
      "high": 125.102031,
      "low": 121.64071,
      "close": 122.629659,
      "volume": 33000.0
    },
    {
      "date": "2024-06-17",
      "open": 123.124134,
      "high": 123.618608,
      "low": 122.135185,
      "close": 122.629659,
      "volume": 20000.0
    },
    {
      "date": "2024-06-18",
      "open": 122.629659,
      "high": 127.079929,
      "low": 122.629659,
      "close": 127.079929,
      "volume": 42000.0
    },
    {
      "date": "2024-06-19",
      "open": 124.113082,
      "high": 129.552301,
      "low": 122.629659,
      "close": 127.574403,
      "volume": 101000.0
    },
    {
      "date": "2024-06-20",
      "open": 124.607557,
      "high": 125.596506,
      "low": 123.618608,
      "close": 125.102031,
      "volume": 39000.0
    },
    {
      "date": "2024-06-21",
      "open": 124.113082,
      "high": 125.102031,
      "low": 123.124134,
      "close": 125.102031,
      "volume": 14000.0
    },
    {
      "date": "2024-06-24",
      "open": 125.102031,
      "high": 126.09098,
      "low": 123.618608,
      "close": 125.596506,
      "volume": 17000.0
    },
    {
      "date": "2024-06-25",
      "open": 125.596506,
      "high": 128.563352,
      "low": 125.596506,
      "close": 127.079929,
      "volume": 35000.0
    },
    {
      "date": "2024-06-26",
      "open": 132.519148,
      "high": 139.44179,
      "low": 132.519148,
      "close": 138.452841,
      "volume": 124000.0
    },
    {
      "date": "2024-06-27",
      "open": 137.463892,
      "high": 138.452841,
      "low": 132.024673,
      "close": 133.508097,
      "volume": 70000.0
    },
    {
      "date": "2024-06-28",
      "open": 136.474943,
      "high": 136.474943,
      "low": 133.013622,
      "close": 134.497045,
      "volume": 18000.0
    },
    {
      "date": "2024-07-01",
      "open": 134.99152,
      "high": 134.99152,
      "low": 131.530199,
      "close": 131.530199,
      "volume": 17000.0
    },
    {
      "date": "2024-07-02",
      "open": 131.530199,
      "high": 131.530199,
      "low": 127.574403,
      "close": 129.552301,
      "volume": 28000.0
    },
    {
      "date": "2024-07-03",
      "open": 129.552301,
      "high": 130.046776,
      "low": 128.563352,
      "close": 130.046776,
      "volume": 23000.0
    },
    {
      "date": "2024-07-04",
      "open": 127.574403,
      "high": 130.54125,
      "low": 127.079929,
      "close": 130.54125,
      "volume": 20225.0
    },
    {
      "date": "2024-07-05",
      "open": 129.552301,
      "high": 130.54125,
      "low": 128.563352,
      "close": 128.563352,
      "volume": 23000.0
    },
    {
      "date": "2024-07-08",
      "open": 128.563352,
      "high": 130.046776,
      "low": 127.574403,
      "close": 130.046776,
      "volume": 24000.0
    },
    {
      "date": "2024-07-09",
      "open": 130.046776,
      "high": 130.046776,
      "low": 127.574403,
      "close": 127.574403,
      "volume": 26000.0
    },
    {
      "date": "2024-07-10",
      "open": 127.574403,
      "high": 128.068878,
      "low": 127.079929,
      "close": 127.574403,
      "volume": 19000.0
    },
    {
      "date": "2024-07-11",
      "open": 128.068878,
      "high": 128.563352,
      "low": 127.574403,
      "close": 128.563352,
      "volume": 19000.0
    },
    {
      "date": "2024-07-12",
      "open": 127.574403,
      "high": 127.574403,
      "low": 126.09098,
      "close": 126.585455,
      "volume": 23000.0
    },
    {
      "date": "2024-07-15",
      "open": 125.596506,
      "high": 126.09098,
      "low": 125.102031,
      "close": 125.102031,
      "volume": 21000.0
    },
    {
      "date": "2024-07-16",
      "open": 126.09098,
      "high": 126.09098,
      "low": 124.607557,
      "close": 124.607557,
      "volume": 18000.0
    },
    {
      "date": "2024-07-17",
      "open": 123.618608,
      "high": 124.113082,
      "low": 121.146236,
      "close": 124.113082,
      "volume": 49000.0
    },
    {
      "date": "2024-07-18",
      "open": 123.124134,
      "high": 123.618608,
      "low": 116.695966,
      "close": 119.168338,
      "volume": 148000.0
    },
    {
      "date": "2024-07-19",
      "open": 117.19044,
      "high": 118.179389,
      "low": 113.729119,
      "close": 115.707017,
      "volume": 38000.0
    },
    {
      "date": "2024-07-22",
      "open": 114.718068,
      "high": 115.212543,
      "low": 104.334105,
      "close": 104.334105,
      "volume": 83000.0
    },
    {
      "date": "2024-07-23",
      "open": 104.334105,
      "high": 113.234645,
      "low": 103.345156,
      "close": 112.245696,
      "volume": 47000.0
    },
    {
      "date": "2024-07-26",
      "open": 111.751222,
      "high": 111.751222,
      "low": 108.289901,
      "close": 111.256747,
      "volume": 17000.0
    },
    {
      "date": "2024-07-29",
      "open": 111.751222,
      "high": 111.751222,
      "low": 111.256747,
      "close": 111.256747,
      "volume": 3000.0
    },
    {
      "date": "2024-07-30",
      "open": 113.729119,
      "high": 114.718068,
      "low": 111.751222,
      "close": 112.74017,
      "volume": 11000.0
    },
    {
      "date": "2024-07-31",
      "open": 113.729119,
      "high": 113.729119,
      "low": 112.245696,
      "close": 112.245696,
      "volume": 7000.0
    },
    {
      "date": "2024-08-01",
      "open": 112.245696,
      "high": 114.718068,
      "low": 111.256747,
      "close": 112.245696,
      "volume": 31000.0
    },
    {
      "date": "2024-08-02",
      "open": 111.256747,
      "high": 111.751222,
      "low": 109.278849,
      "close": 109.278849,
      "volume": 12000.0
    },
    {
      "date": "2024-08-05",
      "open": 100.37831,
      "high": 103.839631,
      "low": 98.400412,
      "close": 103.839631,
      "volume": 75000.0
    },
    {
      "date": "2024-08-06",
      "open": 98.894886,
      "high": 98.894886,
      "low": 93.455668,
      "close": 97.905938,
      "volume": 76000.0
    },
    {
      "date": "2024-08-07",
      "open": 94.741301,
      "high": 96.719199,
      "low": 89.994347,
      "close": 95.33467,
      "volume": 49000.0
    },
    {
      "date": "2024-08-08",
      "open": 94.246827,
      "high": 95.037986,
      "low": 92.466719,
      "close": 95.037986,
      "volume": 7000.0
    },
    {
      "date": "2024-08-09",
      "open": 95.433565,
      "high": 101.861733,
      "low": 95.433565,
      "close": 101.367259,
      "volume": 28000.0
    },
    {
      "date": "2024-08-12",
      "open": 101.367259,
      "high": 101.861733,
      "low": 100.872784,
      "close": 101.367259,
      "volume": 30000.0
    },
    {
      "date": "2024-08-13",
      "open": 100.37831,
      "high": 102.356207,
      "low": 100.37831,
      "close": 100.872784,
      "volume": 24000.0
    },
    {
      "date": "2024-08-14",
      "open": 99.883835,
      "high": 100.872784,
      "low": 99.883835,
      "close": 100.37831,
      "volume": 9000.0
    },
    {
      "date": "2024-08-15",
      "open": 99.883835,
      "high": 100.872784,
      "low": 99.883835,
      "close": 100.872784,
      "volume": 19100.0
    },
    {
      "date": "2024-08-16",
      "open": 101.367259,
      "high": 104.82858,
      "low": 101.367259,
      "close": 104.82858,
      "volume": 15023.0
    },
    {
      "date": "2024-08-19",
      "open": 101.367259,
      "high": 101.367259,
      "low": 97.905938,
      "close": 100.37831,
      "volume": 30092.0
    },
    {
      "date": "2024-08-20",
      "open": 97.114778,
      "high": 98.894886,
      "low": 97.114778,
      "close": 98.795991,
      "volume": 18000.0
    },
    {
      "date": "2024-08-21",
      "open": 98.795991,
      "high": 99.389361,
      "low": 98.499307,
      "close": 99.389361,
      "volume": 19000.0
    },
    {
      "date": "2024-08-22",
      "open": 98.894886,
      "high": 98.894886,
      "low": 97.905938,
      "close": 98.894886,
      "volume": 23000.0
    },
    {
      "date": "2024-08-23",
      "open": 104.334105,
      "high": 104.334105,
      "low": 98.004832,
      "close": 100.872784,
      "volume": 10000.0
    },
    {
      "date": "2024-08-26",
      "open": 99.389361,
      "high": 99.389361,
      "low": 97.905938,
      "close": 98.795991,
      "volume": 43000.0
    },
    {
      "date": "2024-08-27",
      "open": 98.004832,
      "high": 98.004832,
      "low": 96.719199,
      "close": 96.719199,
      "volume": 8000.0
    },
    {
      "date": "2024-08-28",
      "open": 95.433565,
      "high": 98.103727,
      "low": 95.433565,
      "close": 98.103727,
      "volume": 10000.0
    },
    {
      "date": "2024-08-29",
      "open": 96.224724,
      "high": 98.103727,
      "low": 96.224724,
      "close": 98.103727,
      "volume": 2000.0
    },
    {
      "date": "2024-08-30",
      "open": 97.905938,
      "high": 97.905938,
      "low": 97.411463,
      "close": 97.905938,
      "volume": 5000.0
    },
    {
      "date": "2024-09-02",
      "open": 99.389361,
      "high": 99.389361,
      "low": 95.235776,
      "close": 95.73025,
      "volume": 10000.0
    },
    {
      "date": "2024-09-03",
      "open": 92.961193,
      "high": 95.73025,
      "low": 92.862298,
      "close": 92.961193,
      "volume": 18000.0
    },
    {
      "date": "2024-09-04",
      "open": 88.906503,
      "high": 97.807043,
      "low": 88.906503,
      "close": 89.994347,
      "volume": 35000.0
    },
    {
      "date": "2024-09-05",
      "open": 90.192136,
      "high": 90.192136,
      "low": 88.115344,
      "close": 88.214239,
      "volume": 19000.0
    },
    {
      "date": "2024-09-06",
      "open": 87.818659,
      "high": 87.818659,
      "low": 87.818659,
      "close": 87.818659,
      "volume": 1000.0
    },
    {
      "date": "2024-09-09",
      "open": 86.533026,
      "high": 87.521974,
      "low": 82.082756,
      "close": 85.049602,
      "volume": 50000.0
    },
    {
      "date": "2024-09-10",
      "open": 84.159548,
      "high": 84.159548,
      "low": 81.093807,
      "close": 83.071705,
      "volume": 16000.0
    },
    {
      "date": "2024-09-11",
      "open": 80.896017,
      "high": 80.896017,
      "low": 79.907068,
      "close": 79.907068,
      "volume": 7000.0
    },
    {
      "date": "2024-09-12",
      "open": 79.907068,
      "high": 87.719764,
      "low": 79.907068,
      "close": 85.741866,
      "volume": 34000.0
    },
    {
      "date": "2024-09-13",
      "open": 83.961759,
      "high": 84.060653,
      "low": 82.280545,
      "close": 82.280545,
      "volume": 29000.0
    },
    {
      "date": "2024-09-16",
      "open": 81.983861,
      "high": 81.983861,
      "low": 77.138011,
      "close": 81.588281,
      "volume": 64000.0
    },
    {
      "date": "2024-09-18",
      "open": 81.786071,
      "high": 83.071705,
      "low": 81.093807,
      "close": 81.093807,
      "volume": 12000.0
    },
    {
      "date": "2024-09-19",
      "open": 81.093807,
      "high": 81.588281,
      "low": 80.203753,
      "close": 80.203753,
      "volume": 16000.0
    },
    {
      "date": "2024-09-20",
      "open": 81.588281,
      "high": 81.588281,
      "low": 80.203753,
      "close": 81.093807,
      "volume": 11000.0
    },
    {
      "date": "2024-09-23",
      "open": 81.093807,
      "high": 81.093807,
      "low": 81.093807,
      "close": 81.093807,
      "volume": 1000.0
    },
    {
      "date": "2024-09-24",
      "open": 81.093807,
      "high": 81.093807,
      "low": 79.907068,
      "close": 80.005963,
      "volume": 16000.0
    },
    {
      "date": "2024-09-25",
      "open": 80.104858,
      "high": 80.104858,
      "low": 79.115909,
      "close": 80.104858,
      "volume": 31199.0
    },
    {
      "date": "2024-09-26",
      "open": 80.599332,
      "high": 80.698227,
      "low": 79.017014,
      "close": 79.017014,
      "volume": 45405.0
    },
    {
      "date": "2024-09-27",
      "open": 80.994912,
      "high": 80.994912,
      "low": 78.621435,
      "close": 80.104858,
      "volume": 49131.0
    },
    {
      "date": "2024-09-30",
      "open": 79.115909,
      "high": 79.907068,
      "low": 78.12696,
      "close": 79.907068,
      "volume": 32100.0
    },
    {
      "date": "2024-10-01",
      "open": 79.115909,
      "high": 81.093807,
      "low": 79.115909,
      "close": 81.093807,
      "volume": 10000.0
    },
    {
      "date": "2024-10-04",
      "open": 80.203753,
      "high": 80.302648,
      "low": 79.808173,
      "close": 79.808173,
      "volume": 11000.0
    },
    {
      "date": "2024-10-07",
      "open": 79.214804,
      "high": 81.489386,
      "low": 79.214804,
      "close": 80.599332,
      "volume": 19000.0
    },
    {
      "date": "2024-10-08",
      "open": 81.093807,
      "high": 85.049602,
      "low": 80.698227,
      "close": 85.049602,
      "volume": 37200.0
    },
    {
      "date": "2024-10-09",
      "open": 85.049602,
      "high": 93.554563,
      "low": 85.049602,
      "close": 86.236341,
      "volume": 81000.0
    },
    {
      "date": "2024-10-11",
      "open": 86.236341,
      "high": 88.609818,
      "low": 82.676125,
      "close": 88.609818,
      "volume": 18000.0
    },
    {
      "date": "2024-10-14",
      "open": 87.917554,
      "high": 96.719199,
      "low": 87.917554,
      "close": 94.741301,
      "volume": 83271.0
    },
    {
      "date": "2024-10-15",
      "open": 94.939091,
      "high": 94.939091,
      "low": 91.08219,
      "close": 92.466719,
      "volume": 30325.0
    },
    {
      "date": "2024-10-16",
      "open": 92.466719,
      "high": 92.664509,
      "low": 89.895452,
      "close": 92.664509,
      "volume": 9019.0
    },
    {
      "date": "2024-10-17",
      "open": 92.763403,
      "high": 93.257878,
      "low": 90.389926,
      "close": 92.664509,
      "volume": 21000.0
    },
    {
      "date": "2024-10-18",
      "open": 91.774455,
      "high": 93.455668,
      "low": 91.774455,
      "close": 93.060088,
      "volume": 27029.0
    },
    {
      "date": "2024-10-21",
      "open": 93.158983,
      "high": 93.554563,
      "low": 91.47777,
      "close": 92.961193,
      "volume": 39000.0
    },
    {
      "date": "2024-10-22",
      "open": 92.961193,
      "high": 92.961193,
      "low": 91.972244,
      "close": 92.961193,
      "volume": 32000.0
    },
    {
      "date": "2024-10-23",
      "open": 92.961193,
      "high": 92.961193,
      "low": 92.466719,
      "close": 92.862298,
      "volume": 96000.0
    },
    {
      "date": "2024-10-24",
      "open": 92.961193,
      "high": 92.961193,
      "low": 91.972244,
      "close": 92.466719,
      "volume": 58000.0
    },
    {
      "date": "2024-10-25",
      "open": 92.466719,
      "high": 92.466719,
      "low": 92.466719,
      "close": 92.466719,
      "volume": 6000.0
    },
    {
      "date": "2024-10-28",
      "open": 92.763403,
      "high": 92.763403,
      "low": 91.181085,
      "close": 91.181085,
      "volume": 18000.0
    },
    {
      "date": "2024-10-29",
      "open": 90.983295,
      "high": 93.455668,
      "low": 90.983295,
      "close": 90.983295,
      "volume": 16000.0
    },
    {
      "date": "2024-10-30",
      "open": 90.291031,
      "high": 90.488821,
      "low": 90.192136,
      "close": 90.488821,
      "volume": 10000.0
    },
    {
      "date": "2024-11-01",
      "open": 90.093241,
      "high": 91.972244,
      "low": 89.994347,
      "close": 91.972244,
      "volume": 10000.0
    },
    {
      "date": "2024-11-04",
      "open": 94.049037,
      "high": 94.049037,
      "low": 94.049037,
      "close": 94.049037,
      "volume": 1000.0
    },
    {
      "date": "2024-11-05",
      "open": 93.950142,
      "high": 93.950142,
      "low": 91.08219,
      "close": 91.08219,
      "volume": 5000.0
    },
    {
      "date": "2024-11-06",
      "open": 91.181085,
      "high": 91.181085,
      "low": 91.08219,
      "close": 91.08219,
      "volume": 4001.0
    },
    {
      "date": "2024-11-07",
      "open": 91.08219,
      "high": 91.08219,
      "low": 89.994347,
      "close": 89.994347,
      "volume": 9000.0
    },
    {
      "date": "2024-11-08",
      "open": 89.994347,
      "high": 89.994347,
      "low": 88.313134,
      "close": 88.313134,
      "volume": 3653.0
    },
    {
      "date": "2024-11-11",
      "open": 88.313134,
      "high": 88.313134,
      "low": 88.313134,
      "close": 88.313134,
      "volume": 5000.0
    },
    {
      "date": "2024-11-12",
      "open": 88.313134,
      "high": 88.412028,
      "low": 88.016449,
      "close": 88.016449,
      "volume": 14000.0
    },
    {
      "date": "2024-11-13",
      "open": 88.016449,
      "high": 88.115344,
      "low": 87.0275,
      "close": 87.521974,
      "volume": 19000.0
    },
    {
      "date": "2024-11-14",
      "open": 86.533026,
      "high": 86.63192,
      "low": 86.038551,
      "close": 86.038551,
      "volume": 10000.0
    },
    {
      "date": "2024-11-15",
      "open": 84.060653,
      "high": 88.906503,
      "low": 84.060653,
      "close": 88.906503,
      "volume": 2010.0
    },
    {
      "date": "2024-11-18",
      "open": 88.510923,
      "high": 88.708713,
      "low": 88.510923,
      "close": 88.708713,
      "volume": 2000.0
    },
    {
      "date": "2024-11-19",
      "open": 88.906503,
      "high": 89.005398,
      "low": 85.939656,
      "close": 87.620869,
      "volume": 9000.0
    },
    {
      "date": "2024-11-20",
      "open": 88.807608,
      "high": 88.807608,
      "low": 88.807608,
      "close": 88.807608,
      "volume": 1000.0
    },
    {
      "date": "2024-11-21",
      "open": 88.807608,
      "high": 88.807608,
      "low": 88.807608,
      "close": 88.807608,
      "volume": 0.0
    },
    {
      "date": "2024-11-22",
      "open": 87.126395,
      "high": 88.609818,
      "low": 86.928605,
      "close": 88.609818,
      "volume": 20000.0
    },
    {
      "date": "2024-11-25",
      "open": 89.598767,
      "high": 89.598767,
      "low": 86.335236,
      "close": 86.335236,
      "volume": 19000.0
    },
    {
      "date": "2024-11-26",
      "open": 85.642972,
      "high": 86.137446,
      "low": 85.642972,
      "close": 86.137446,
      "volume": 3000.0
    },
    {
      "date": "2024-11-27",
      "open": 86.137446,
      "high": 86.137446,
      "low": 85.544077,
      "close": 85.544077,
      "volume": 7000.0
    },
    {
      "date": "2024-11-28",
      "open": 84.060653,
      "high": 84.555128,
      "low": 82.082756,
      "close": 84.555128,
      "volume": 23000.0
    },
    {
      "date": "2024-11-29",
      "open": 84.060653,
      "high": 84.555128,
      "low": 82.082756,
      "close": 84.555128,
      "volume": 0.0
    },
    {
      "date": "2024-12-02",
      "open": 84.060653,
      "high": 84.555128,
      "low": 82.082756,
      "close": 84.555128,
      "volume": 681000.0
    },
    {
      "date": "2024-12-03",
      "open": 84.950707,
      "high": 85.148497,
      "low": 84.654023,
      "close": 85.049602,
      "volume": 14000.0
    },
    {
      "date": "2024-12-04",
      "open": 84.950707,
      "high": 85.148497,
      "low": 84.654023,
      "close": 85.049602,
      "volume": 0.0
    },
    {
      "date": "2024-12-05",
      "open": 84.752918,
      "high": 86.038551,
      "low": 82.181651,
      "close": 86.038551,
      "volume": 29000.0
    },
    {
      "date": "2024-12-06",
      "open": 84.159548,
      "high": 86.82971,
      "low": 84.159548,
      "close": 86.533026,
      "volume": 5000.0
    },
    {
      "date": "2024-12-09",
      "open": 84.654023,
      "high": 84.851813,
      "low": 84.555128,
      "close": 84.654023,
      "volume": 4000.0
    },
    {
      "date": "2024-12-10",
      "open": 84.654023,
      "high": 84.654023,
      "low": 84.357338,
      "close": 84.456233,
      "volume": 16000.0
    },
    {
      "date": "2024-12-11",
      "open": 84.456233,
      "high": 84.456233,
      "low": 83.566179,
      "close": 83.566179,
      "volume": 17000.0
    },
    {
      "date": "2024-12-12",
      "open": 88.412028,
      "high": 88.412028,
      "low": 83.170599,
      "close": 83.269494,
      "volume": 36000.0
    },
    {
      "date": "2024-12-13",
      "open": 83.566179,
      "high": 83.566179,
      "low": 83.269494,
      "close": 83.269494,
      "volume": 6000.0
    },
    {
      "date": "2024-12-16",
      "open": 81.687176,
      "high": 82.873915,
      "low": 79.214804,
      "close": 82.873915,
      "volume": 50000.0
    },
    {
      "date": "2024-12-17",
      "open": 82.873915,
      "high": 82.873915,
      "low": 78.819224,
      "close": 82.77502,
      "volume": 58000.0
    },
    {
      "date": "2024-12-18",
      "open": 81.093807,
      "high": 82.57723,
      "low": 80.104858,
      "close": 82.082756,
      "volume": 21000.0
    },
    {
      "date": "2024-12-19",
      "open": 81.093807,
      "high": 82.57723,
      "low": 77.434696,
      "close": 82.57723,
      "volume": 35000.0
    },
    {
      "date": "2024-12-20",
      "open": 79.709278,
      "high": 82.37944,
      "low": 79.610384,
      "close": 79.709278,
      "volume": 11000.0
    },
    {
      "date": "2024-12-23",
      "open": 81.687176,
      "high": 81.687176,
      "low": 79.907068,
      "close": 79.907068,
      "volume": 10000.0
    },
    {
      "date": "2024-12-24",
      "open": 81.093807,
      "high": 81.093807,
      "low": 79.115909,
      "close": 80.302648,
      "volume": 7000.0
    },
    {
      "date": "2024-12-25",
      "open": 79.709278,
      "high": 82.082756,
      "low": 79.115909,
      "close": 82.082756,
      "volume": 16000.0
    },
    {
      "date": "2024-12-26",
      "open": 80.302648,
      "high": 81.588281,
      "low": 79.115909,
      "close": 81.588281,
      "volume": 9000.0
    },
    {
      "date": "2024-12-27",
      "open": 79.115909,
      "high": 81.390491,
      "low": 79.017014,
      "close": 81.093807,
      "volume": 16000.0
    },
    {
      "date": "2024-12-30",
      "open": 79.907068,
      "high": 82.57723,
      "low": 79.214804,
      "close": 79.214804,
      "volume": 17000.0
    },
    {
      "date": "2024-12-31",
      "open": 79.115909,
      "high": 81.093807,
      "low": 79.115909,
      "close": 80.797122,
      "volume": 53000.0
    },
    {
      "date": "2025-01-02",
      "open": 80.698227,
      "high": 80.698227,
      "low": 79.115909,
      "close": 79.115909,
      "volume": 6000.0
    },
    {
      "date": "2025-01-03",
      "open": 79.610384,
      "high": 79.709278,
      "low": 79.017014,
      "close": 79.709278,
      "volume": 35000.0
    },
    {
      "date": "2025-01-06",
      "open": 80.599332,
      "high": 82.57723,
      "low": 80.104858,
      "close": 80.104858,
      "volume": 43062.0
    },
    {
      "date": "2025-01-07",
      "open": 80.104858,
      "high": 80.896017,
      "low": 79.115909,
      "close": 80.896017,
      "volume": 20000.0
    },
    {
      "date": "2025-01-08",
      "open": 80.896017,
      "high": 80.896017,
      "low": 79.017014,
      "close": 79.511489,
      "volume": 45000.0
    },
    {
      "date": "2025-01-09",
      "open": 78.621435,
      "high": 79.214804,
      "low": 78.621435,
      "close": 79.214804,
      "volume": 3000.0
    },
    {
      "date": "2025-01-10",
      "open": 79.412594,
      "high": 80.896017,
      "low": 78.621435,
      "close": 79.115909,
      "volume": 78153.0
    },
    {
      "date": "2025-01-13",
      "open": 77.731381,
      "high": 79.313699,
      "low": 77.632486,
      "close": 79.313699,
      "volume": 4103.0
    },
    {
      "date": "2025-01-14",
      "open": 77.731381,
      "high": 79.313699,
      "low": 77.632486,
      "close": 79.313699,
      "volume": 0.0
    },
    {
      "date": "2025-01-15",
      "open": 78.12696,
      "high": 79.115909,
      "low": 78.12696,
      "close": 79.115909,
      "volume": 3000.0
    },
    {
      "date": "2025-01-16",
      "open": 79.610384,
      "high": 79.610384,
      "low": 79.115909,
      "close": 79.115909,
      "volume": 9000.0
    },
    {
      "date": "2025-01-17",
      "open": 78.32475,
      "high": 79.313699,
      "low": 78.32475,
      "close": 78.423645,
      "volume": 7000.0
    },
    {
      "date": "2025-01-20",
      "open": 79.115909,
      "high": 79.115909,
      "low": 78.12696,
      "close": 78.12696,
      "volume": 29020.0
    },
    {
      "date": "2025-01-21",
      "open": 79.907068,
      "high": 79.907068,
      "low": 77.632486,
      "close": 78.12696,
      "volume": 42008.0
    },
    {
      "date": "2025-01-22",
      "open": 78.32475,
      "high": 78.918119,
      "low": 78.12696,
      "close": 78.12696,
      "volume": 32000.0
    },
    {
      "date": "2025-02-03",
      "open": 78.621435,
      "high": 82.082756,
      "low": 77.632486,
      "close": 82.082756,
      "volume": 48466.0
    },
    {
      "date": "2025-02-04",
      "open": 83.071705,
      "high": 83.071705,
      "low": 81.884966,
      "close": 82.082756,
      "volume": 13100.0
    },
    {
      "date": "2025-02-05",
      "open": 82.37944,
      "high": 87.818659,
      "low": 82.082756,
      "close": 87.818659,
      "volume": 64000.0
    },
    {
      "date": "2025-02-06",
      "open": 89.895452,
      "high": 96.521409,
      "low": 89.895452,
      "close": 96.521409,
      "volume": 114217.0
    },
    {
      "date": "2025-02-07",
      "open": 101.861733,
      "high": 105.323054,
      "low": 98.894886,
      "close": 100.872784,
      "volume": 121148.0
    },
    {
      "date": "2025-02-10",
      "open": 100.872784,
      "high": 100.872784,
      "low": 98.894886,
      "close": 100.872784,
      "volume": 60401.0
    },
    {
      "date": "2025-02-11",
      "open": 100.872784,
      "high": 102.356207,
      "low": 99.389361,
      "close": 100.872784,
      "volume": 44170.0
    },
    {
      "date": "2025-02-12",
      "open": 106.806477,
      "high": 110.762273,
      "low": 106.806477,
      "close": 110.762273,
      "volume": 245744.0
    },
    {
      "date": "2025-02-13",
      "open": 121.64071,
      "high": 121.64071,
      "low": 117.19044,
      "close": 121.64071,
      "volume": 277674.0
    },
    {
      "date": "2025-02-14",
      "open": 131.035724,
      "high": 133.508097,
      "low": 124.607557,
      "close": 128.563352,
      "volume": 462083.0
    },
    {
      "date": "2025-02-17",
      "open": 129.552301,
      "high": 133.508097,
      "low": 121.64071,
      "close": 129.057827,
      "volume": 360515.0
    },
    {
      "date": "2025-02-18",
      "open": 128.563352,
      "high": 128.563352,
      "low": 125.102031,
      "close": 128.068878,
      "volume": 100026.0
    },
    {
      "date": "2025-02-19",
      "open": 125.596506,
      "high": 127.574403,
      "low": 121.146236,
      "close": 127.574403,
      "volume": 250481.0
    },
    {
      "date": "2025-02-20",
      "open": 127.574403,
      "high": 133.013622,
      "low": 127.574403,
      "close": 131.530199,
      "volume": 245068.0
    },
    {
      "date": "2025-02-21",
      "open": 134.002571,
      "high": 144.386534,
      "low": 133.508097,
      "close": 144.386534,
      "volume": 556012.0
    },
    {
      "date": "2025-02-24",
      "open": 148.34233,
      "high": 158.726293,
      "low": 147.353381,
      "close": 157.242869,
      "volume": 520423.0
    },
    {
      "date": "2025-02-25",
      "open": 155.264972,
      "high": 161.693139,
      "low": 150.814702,
      "close": 153.781548,
      "volume": 294526.0
    },
    {
      "date": "2025-02-26",
      "open": 153.781548,
      "high": 154.276023,
      "low": 148.34233,
      "close": 152.792599,
      "volume": 136052.0
    },
    {
      "date": "2025-02-27",
      "open": 155.264972,
      "high": 157.737344,
      "low": 150.320227,
      "close": 155.759446,
      "volume": 240593.0
    },
    {
      "date": "2025-03-03",
      "open": 153.287074,
      "high": 154.770497,
      "low": 143.89206,
      "close": 150.320227,
      "volume": 208663.0
    },
    {
      "date": "2025-03-04",
      "open": 147.353381,
      "high": 155.264972,
      "low": 146.364432,
      "close": 153.781548,
      "volume": 207443.0
    },
    {
      "date": "2025-03-05",
      "open": 152.792599,
      "high": 152.792599,
      "low": 149.331278,
      "close": 150.320227,
      "volume": 88222.0
    },
    {
      "date": "2025-03-06",
      "open": 153.781548,
      "high": 153.781548,
      "low": 148.34233,
      "close": 148.836804,
      "volume": 93637.0
    },
    {
      "date": "2025-03-07",
      "open": 147.353381,
      "high": 151.803651,
      "low": 147.353381,
      "close": 148.34233,
      "volume": 56766.0
    },
    {
      "date": "2025-03-10",
      "open": 148.34233,
      "high": 148.34233,
      "low": 138.452841,
      "close": 146.364432,
      "volume": 174971.0
    },
    {
      "date": "2025-03-11",
      "open": 140.430739,
      "high": 146.364432,
      "low": 136.969418,
      "close": 143.89206,
      "volume": 109619.0
    },
    {
      "date": "2025-03-12",
      "open": 143.89206,
      "high": 144.881009,
      "low": 140.430739,
      "close": 143.89206,
      "volume": 54902.0
    },
    {
      "date": "2025-03-13",
      "open": 143.89206,
      "high": 144.386534,
      "low": 137.463892,
      "close": 141.914162,
      "volume": 90589.0
    },
    {
      "date": "2025-03-14",
      "open": 141.914162,
      "high": 143.397585,
      "low": 135.980469,
      "close": 143.397585,
      "volume": 107934.0
    },
    {
      "date": "2025-03-17",
      "open": 143.397585,
      "high": 143.397585,
      "low": 140.430739,
      "close": 140.430739,
      "volume": 51654.0
    },
    {
      "date": "2025-03-18",
      "open": 138.947315,
      "high": 139.44179,
      "low": 137.958366,
      "close": 139.44179,
      "volume": 72132.0
    },
    {
      "date": "2025-03-19",
      "open": 137.463892,
      "high": 137.463892,
      "low": 131.530199,
      "close": 134.002571,
      "volume": 199821.0
    },
    {
      "date": "2025-03-20",
      "open": 133.508097,
      "high": 147.353381,
      "low": 132.024673,
      "close": 147.353381,
      "volume": 323240.0
    },
    {
      "date": "2025-03-21",
      "open": 148.34233,
      "high": 151.309176,
      "low": 140.925213,
      "close": 144.881009,
      "volume": 202894.0
    },
    {
      "date": "2025-03-24",
      "open": 148.836804,
      "high": 148.836804,
      "low": 138.452841,
      "close": 142.408636,
      "volume": 130392.0
    },
    {
      "date": "2025-03-25",
      "open": 143.397585,
      "high": 145.375483,
      "low": 138.452841,
      "close": 143.397585,
      "volume": 147660.0
    },
    {
      "date": "2025-03-26",
      "open": 142.903111,
      "high": 152.792599,
      "low": 140.430739,
      "close": 149.825753,
      "volume": 164234.0
    },
    {
      "date": "2025-03-27",
      "open": 147.353381,
      "high": 147.353381,
      "low": 143.397585,
      "close": 143.397585,
      "volume": 62128.0
    },
    {
      "date": "2025-03-28",
      "open": 141.419688,
      "high": 145.869957,
      "low": 136.474943,
      "close": 140.925213,
      "volume": 126372.0
    },
    {
      "date": "2025-03-31",
      "open": 136.474943,
      "high": 143.89206,
      "low": 134.497045,
      "close": 141.419688,
      "volume": 126006.0
    },
    {
      "date": "2025-04-01",
      "open": 137.463892,
      "high": 140.925213,
      "low": 137.463892,
      "close": 139.44179,
      "volume": 40195.0
    },
    {
      "date": "2025-04-02",
      "open": 139.44179,
      "high": 139.936264,
      "low": 137.958366,
      "close": 139.936264,
      "volume": 25708.0
    },
    {
      "date": "2025-04-07",
      "open": 126.09098,
      "high": 126.09098,
      "low": 126.09098,
      "close": 126.09098,
      "volume": 9460.0
    },
    {
      "date": "2025-04-08",
      "open": 114.718068,
      "high": 118.673864,
      "low": 113.729119,
      "close": 115.707017,
      "volume": 156895.0
    },
    {
      "date": "2025-04-09",
      "open": 104.334105,
      "high": 108.784375,
      "low": 104.334105,
      "close": 104.334105,
      "volume": 111569.0
    },
    {
      "date": "2025-04-10",
      "open": 113.729119,
      "high": 114.718068,
      "low": 113.729119,
      "close": 114.718068,
      "volume": 16902.0
    },
    {
      "date": "2025-04-11",
      "open": 113.729119,
      "high": 117.19044,
      "low": 108.784375,
      "close": 115.707017,
      "volume": 78712.0
    },
    {
      "date": "2025-04-14",
      "open": 121.146236,
      "high": 122.629659,
      "low": 111.256747,
      "close": 116.201491,
      "volume": 115761.0
    },
    {
      "date": "2025-04-15",
      "open": 116.201491,
      "high": 127.079929,
      "low": 115.707017,
      "close": 125.596506,
      "volume": 61791.0
    },
    {
      "date": "2025-04-16",
      "open": 124.113082,
      "high": 124.113082,
      "low": 122.135185,
      "close": 123.618608,
      "volume": 33305.0
    },
    {
      "date": "2025-04-17",
      "open": 121.64071,
      "high": 133.508097,
      "low": 121.146236,
      "close": 124.113082,
      "volume": 136417.0
    },
    {
      "date": "2025-04-18",
      "open": 124.607557,
      "high": 125.102031,
      "low": 121.64071,
      "close": 124.113082,
      "volume": 20020.0
    },
    {
      "date": "2025-04-21",
      "open": 120.651761,
      "high": 121.64071,
      "low": 117.19044,
      "close": 121.146236,
      "volume": 63150.0
    },
    {
      "date": "2025-04-22",
      "open": 119.662813,
      "high": 123.124134,
      "low": 117.684915,
      "close": 120.651761,
      "volume": 85064.0
    },
    {
      "date": "2025-04-23",
      "open": 122.135185,
      "high": 126.09098,
      "low": 120.157287,
      "close": 121.64071,
      "volume": 73145.0
    },
    {
      "date": "2025-04-24",
      "open": 121.146236,
      "high": 121.64071,
      "low": 119.662812,
      "close": 120.651761,
      "volume": 24182.0
    },
    {
      "date": "2025-04-25",
      "open": 121.64071,
      "high": 122.629659,
      "low": 118.673864,
      "close": 119.662812,
      "volume": 79314.0
    },
    {
      "date": "2025-04-28",
      "open": 119.662812,
      "high": 125.596506,
      "low": 119.662812,
      "close": 125.596506,
      "volume": 71872.0
    },
    {
      "date": "2025-04-29",
      "open": 125.596506,
      "high": 128.068878,
      "low": 125.596506,
      "close": 127.574403,
      "volume": 42124.0
    },
    {
      "date": "2025-04-30",
      "open": 127.574403,
      "high": 133.508097,
      "low": 124.607557,
      "close": 127.079929,
      "volume": 95971.0
    },
    {
      "date": "2025-05-02",
      "open": 124.113082,
      "high": 130.54125,
      "low": 124.113082,
      "close": 130.54125,
      "volume": 61221.0
    },
    {
      "date": "2025-05-05",
      "open": 130.046776,
      "high": 130.046776,
      "low": 122.629659,
      "close": 128.563352,
      "volume": 78494.0
    },
    {
      "date": "2025-05-06",
      "open": 125.102031,
      "high": 128.068878,
      "low": 125.102031,
      "close": 128.068878,
      "volume": 16000.0
    },
    {
      "date": "2025-05-07",
      "open": 124.607557,
      "high": 126.09098,
      "low": 122.629659,
      "close": 122.629659,
      "volume": 46575.0
    },
    {
      "date": "2025-05-08",
      "open": 122.629659,
      "high": 126.585455,
      "low": 122.135185,
      "close": 123.618608,
      "volume": 33278.0
    },
    {
      "date": "2025-05-09",
      "open": 122.629659,
      "high": 123.618608,
      "low": 121.146236,
      "close": 123.618608,
      "volume": 48020.0
    },
    {
      "date": "2025-05-12",
      "open": 124.113082,
      "high": 134.497045,
      "low": 124.113082,
      "close": 131.530199,
      "volume": 209129.0
    },
    {
      "date": "2025-05-13",
      "open": 133.013622,
      "high": 133.508097,
      "low": 128.563352,
      "close": 132.519148,
      "volume": 112703.0
    },
    {
      "date": "2025-05-14",
      "open": 131.035724,
      "high": 131.035724,
      "low": 124.607557,
      "close": 128.563352,
      "volume": 182612.0
    },
    {
      "date": "2025-05-15",
      "open": 127.079929,
      "high": 129.057827,
      "low": 124.607557,
      "close": 128.563352,
      "volume": 131453.0
    },
    {
      "date": "2025-05-16",
      "open": 126.09098,
      "high": 127.574403,
      "low": 124.607557,
      "close": 127.079929,
      "volume": 53463.0
    },
    {
      "date": "2025-05-19",
      "open": 125.596506,
      "high": 127.079929,
      "low": 124.607557,
      "close": 126.585455,
      "volume": 13050.0
    },
    {
      "date": "2025-05-20",
      "open": 126.585455,
      "high": 126.585455,
      "low": 125.102031,
      "close": 125.596506,
      "volume": 16310.0
    },
    {
      "date": "2025-05-21",
      "open": 124.113082,
      "high": 126.585455,
      "low": 123.618608,
      "close": 125.102031,
      "volume": 151060.0
    },
    {
      "date": "2025-05-22",
      "open": 124.113082,
      "high": 127.079929,
      "low": 124.113082,
      "close": 125.596506,
      "volume": 46006.0
    },
    {
      "date": "2025-05-23",
      "open": 127.079929,
      "high": 127.079929,
      "low": 126.585455,
      "close": 126.585455,
      "volume": 8106.0
    },
    {
      "date": "2025-05-26",
      "open": 126.585455,
      "high": 132.024673,
      "low": 126.585455,
      "close": 130.54125,
      "volume": 82503.0
    },
    {
      "date": "2025-05-27",
      "open": 129.552301,
      "high": 129.552301,
      "low": 127.574403,
      "close": 129.057827,
      "volume": 24802.0
    },
    {
      "date": "2025-05-28",
      "open": 129.552301,
      "high": 134.497045,
      "low": 129.552301,
      "close": 134.497045,
      "volume": 100037.0
    },
    {
      "date": "2025-05-29",
      "open": 134.497045,
      "high": 134.497045,
      "low": 131.035724,
      "close": 134.497045,
      "volume": 46270.0
    },
    {
      "date": "2025-06-02",
      "open": 132.024673,
      "high": 133.013622,
      "low": 129.057827,
      "close": 133.013622,
      "volume": 51552.0
    },
    {
      "date": "2025-06-03",
      "open": 131.530199,
      "high": 135.485994,
      "low": 131.530199,
      "close": 135.485994,
      "volume": 75079.0
    },
    {
      "date": "2025-06-04",
      "open": 134.99152,
      "high": 138.452841,
      "low": 134.99152,
      "close": 137.463892,
      "volume": 169266.0
    },
    {
      "date": "2025-06-05",
      "open": 137.958366,
      "high": 137.958366,
      "low": 137.463892,
      "close": 137.463892,
      "volume": 86351.0
    },
    {
      "date": "2025-06-06",
      "open": 136.474943,
      "high": 138.947315,
      "low": 136.474943,
      "close": 137.958366,
      "volume": 105470.0
    },
    {
      "date": "2025-06-09",
      "open": 137.958366,
      "high": 137.958366,
      "low": 135.980469,
      "close": 136.969418,
      "volume": 73285.0
    },
    {
      "date": "2025-06-10",
      "open": 135.485994,
      "high": 136.474943,
      "low": 134.002571,
      "close": 135.980469,
      "volume": 114485.0
    },
    {
      "date": "2025-06-11",
      "open": 140.925213,
      "high": 140.925213,
      "low": 134.497045,
      "close": 140.430739,
      "volume": 114558.0
    },
    {
      "date": "2025-06-12",
      "open": 137.463892,
      "high": 139.44179,
      "low": 135.980469,
      "close": 136.474943,
      "volume": 124717.0
    },
    {
      "date": "2025-06-13",
      "open": 135.980469,
      "high": 139.44179,
      "low": 135.980469,
      "close": 138.452841,
      "volume": 52040.0
    },
    {
      "date": "2025-06-16",
      "open": 141.419688,
      "high": 141.419688,
      "low": 135.980469,
      "close": 138.452841,
      "volume": 35202.0
    },
    {
      "date": "2025-06-17",
      "open": 136.474943,
      "high": 137.958366,
      "low": 134.99152,
      "close": 137.958366,
      "volume": 21080.0
    },
    {
      "date": "2025-06-18",
      "open": 136.474943,
      "high": 136.474943,
      "low": 135.980469,
      "close": 135.980469,
      "volume": 26046.0
    },
    {
      "date": "2025-06-19",
      "open": 135.485994,
      "high": 135.485994,
      "low": 131.035724,
      "close": 134.002571,
      "volume": 105477.0
    },
    {
      "date": "2025-06-20",
      "open": 137.463892,
      "high": 137.463892,
      "low": 126.585455,
      "close": 131.530199,
      "volume": 60513.0
    },
    {
      "date": "2025-06-23",
      "open": 125.596506,
      "high": 132.519148,
      "low": 125.596506,
      "close": 132.519148,
      "volume": 30500.0
    },
    {
      "date": "2025-06-24",
      "open": 130.046776,
      "high": 135.485994,
      "low": 130.046776,
      "close": 135.485994,
      "volume": 88182.0
    },
    {
      "date": "2025-06-25",
      "open": 134.99152,
      "high": 135.485994,
      "low": 132.024673,
      "close": 134.002571,
      "volume": 40326.0
    },
    {
      "date": "2025-06-26",
      "open": 134.002571,
      "high": 135.980469,
      "low": 131.530199,
      "close": 134.497045,
      "volume": 44100.0
    },
    {
      "date": "2025-06-27",
      "open": 134.497045,
      "high": 140.430739,
      "low": 134.497045,
      "close": 138.452841,
      "volume": 220947.0
    },
    {
      "date": "2025-06-30",
      "open": 141.419688,
      "high": 152.298125,
      "low": 141.419688,
      "close": 149.331278,
      "volume": 318780.0
    },
    {
      "date": "2025-07-01",
      "open": 149.331278,
      "high": 156.25392,
      "low": 147.847855,
      "close": 153.781548,
      "volume": 316903.0
    },
    {
      "date": "2025-07-02",
      "open": 153.781548,
      "high": 158.726293,
      "low": 152.298125,
      "close": 156.748395,
      "volume": 244248.0
    },
    {
      "date": "2025-07-03",
      "open": 160.209716,
      "high": 161.693139,
      "low": 155.264972,
      "close": 155.264972,
      "volume": 219346.0
    },
    {
      "date": "2025-07-04",
      "open": 157.242869,
      "high": 157.242869,
      "low": 149.331278,
      "close": 155.759446,
      "volume": 152692.0
    },
    {
      "date": "2025-07-07",
      "open": 162.187614,
      "high": 162.187614,
      "low": 152.298125,
      "close": 153.781548,
      "volume": 93118.0
    },
    {
      "date": "2025-07-08",
      "open": 157.242869,
      "high": 157.242869,
      "low": 149.825753,
      "close": 151.309176,
      "volume": 63508.0
    },
    {
      "date": "2025-07-09",
      "open": 151.309176,
      "high": 156.748395,
      "low": 151.309176,
      "close": 155.759446,
      "volume": 82207.0
    },
    {
      "date": "2025-07-10",
      "open": 155.264972,
      "high": 160.209716,
      "low": 154.770497,
      "close": 158.726293,
      "volume": 166754.0
    },
    {
      "date": "2025-07-11",
      "open": 158.726293,
      "high": 160.70419,
      "low": 155.264972,
      "close": 157.737344,
      "volume": 140917.0
    },
    {
      "date": "2025-07-14",
      "open": 154.276023,
      "high": 157.242869,
      "low": 153.287074,
      "close": 157.242869,
      "volume": 86431.0
    },
    {
      "date": "2025-07-15",
      "open": 156.748395,
      "high": 157.242869,
      "low": 152.792599,
      "close": 157.242869,
      "volume": 95133.0
    },
    {
      "date": "2025-07-16",
      "open": 158.231818,
      "high": 159.220767,
      "low": 154.770497,
      "close": 158.231818,
      "volume": 192152.0
    },
    {
      "date": "2025-07-17",
      "open": 158.231818,
      "high": 158.726293,
      "low": 155.264972,
      "close": 157.242869,
      "volume": 62003.0
    },
    {
      "date": "2025-07-18",
      "open": 157.242869,
      "high": 158.231818,
      "low": 154.770497,
      "close": 156.748395,
      "volume": 78329.0
    },
    {
      "date": "2025-07-21",
      "open": 154.276023,
      "high": 157.242869,
      "low": 153.781548,
      "close": 156.25392,
      "volume": 87500.0
    },
    {
      "date": "2025-07-22",
      "open": 155.264972,
      "high": 157.242869,
      "low": 152.298125,
      "close": 154.276023,
      "volume": 160695.0
    },
    {
      "date": "2025-07-23",
      "open": 154.770497,
      "high": 157.737344,
      "low": 153.287074,
      "close": 154.276023,
      "volume": 119180.0
    },
    {
      "date": "2025-07-24",
      "open": 154.276023,
      "high": 169.60473,
      "low": 154.276023,
      "close": 168.121307,
      "volume": 357341.0
    },
    {
      "date": "2025-07-25",
      "open": 166.143409,
      "high": 178.010795,
      "low": 162.187614,
      "close": 167.132358,
      "volume": 373196.0
    },
    {
      "date": "2025-07-28",
      "open": 164.659986,
      "high": 169.110256,
      "low": 162.187614,
      "close": 167.132358,
      "volume": 86379.0
    },
    {
      "date": "2025-07-29",
      "open": 169.60473,
      "high": 169.60473,
      "low": 165.648935,
      "close": 167.132358,
      "volume": 44879.0
    },
    {
      "date": "2025-07-30",
      "open": 167.132358,
      "high": 183.450014,
      "low": 167.132358,
      "close": 183.450014,
      "volume": 598839.0
    },
    {
      "date": "2025-07-31",
      "open": 186.911335,
      "high": 195.811875,
      "low": 181.472116,
      "close": 190.867131,
      "volume": 454590.0
    },
    {
      "date": "2025-08-01",
      "open": 187.900284,
      "high": 209.657159,
      "low": 187.900284,
      "close": 209.657159,
      "volume": 399027.0
    },
    {
      "date": "2025-08-04",
      "open": 230.425085,
      "high": 230.425085,
      "low": 230.425085,
      "close": 230.425085,
      "volume": 153573.0
    },
    {
      "date": "2025-08-05",
      "open": 253.170909,
      "high": 253.170909,
      "low": 253.170909,
      "close": 253.170909,
      "volume": 75724.0
    },
    {
      "date": "2025-08-06",
      "open": 278.389105,
      "high": 278.389105,
      "low": 278.389105,
      "close": 278.389105,
      "volume": 69571.0
    },
    {
      "date": "2025-08-07",
      "open": 306.079673,
      "high": 306.079673,
      "low": 292.728864,
      "close": 306.079673,
      "volume": 899257.0
    },
    {
      "date": "2025-08-08",
      "open": 311.518892,
      "high": 335.748139,
      "low": 311.518892,
      "close": 335.253665,
      "volume": 723820.0
    },
    {
      "date": "2025-08-11",
      "open": 336.242614,
      "high": 362.449759,
      "low": 322.39733,
      "close": 356.021591,
      "volume": 598958.0
    },
    {
      "date": "2025-08-12",
      "open": 356.021591,
      "high": 390.634801,
      "low": 356.021591,
      "close": 390.634801,
      "volume": 355697.0
    },
    {
      "date": "2025-08-13",
      "open": 390.634801,
      "high": 409.42483,
      "low": 351.571321,
      "close": 351.571321,
      "volume": 261822.0
    },
    {
      "date": "2025-08-14",
      "open": 326.353125,
      "high": 356.516065,
      "low": 326.353125,
      "close": 351.571321,
      "volume": 535179.0
    },
    {
      "date": "2025-08-15",
      "open": 352.065795,
      "high": 353.054744,
      "low": 346.132102,
      "close": 347.121051,
      "volume": 196479.0
    },
    {
      "date": "2025-08-18",
      "open": 351.076847,
      "high": 351.076847,
      "low": 332.781293,
      "close": 337.231562,
      "volume": 350922.0
    },
    {
      "date": "2025-08-19",
      "open": 340.198409,
      "high": 346.132102,
      "low": 335.253665,
      "close": 346.132102,
      "volume": 273495.0
    },
    {
      "date": "2025-08-20",
      "open": 346.132102,
      "high": 346.132102,
      "low": 338.220511,
      "close": 341.187358,
      "volume": 279700.0
    },
    {
      "date": "2025-08-21",
      "open": 341.187358,
      "high": 351.571321,
      "low": 341.187358,
      "close": 351.571321,
      "volume": 412417.0
    },
    {
      "date": "2025-08-22",
      "open": 360.966335,
      "high": 386.679006,
      "low": 360.966335,
      "close": 386.679006,
      "volume": 340265.0
    },
    {
      "date": "2025-08-25",
      "open": 423.270114,
      "high": 423.270114,
      "low": 380.745313,
      "close": 385.690057,
      "volume": 1064421.0
    },
    {
      "date": "2025-08-26",
      "open": 388.162429,
      "high": 395.579545,
      "low": 356.516065,
      "close": 389.645852,
      "volume": 1029764.0
    },
    {
      "date": "2025-08-27",
      "open": 389.645852,
      "high": 428.214858,
      "low": 381.734261,
      "close": 423.270114,
      "volume": 593633.0
    },
    {
      "date": "2025-08-28",
      "open": 434.148551,
      "high": 452.93858,
      "low": 410.908253,
      "close": 415.358523,
      "volume": 458869.0
    },
    {
      "date": "2025-08-29",
      "open": 418.325369,
      "high": 420.303267,
      "low": 396.07402,
      "close": 399.040866,
      "volume": 286282.0
    },
    {
      "date": "2025-09-01",
      "open": 400.52429,
      "high": 400.52429,
      "low": 376.789517,
      "close": 386.679006,
      "volume": 198276.0
    },
    {
      "date": "2025-09-02",
      "open": 395.579545,
      "high": 399.535341,
      "low": 367.888977,
      "close": 390.140327,
      "volume": 195603.0
    },
    {
      "date": "2025-09-03",
      "open": 392.612699,
      "high": 403.491136,
      "low": 381.734261,
      "close": 403.491136,
      "volume": 145004.0
    },
    {
      "date": "2025-09-04",
      "open": 414.864048,
      "high": 414.864048,
      "low": 399.040866,
      "close": 405.469034,
      "volume": 192418.0
    },
    {
      "date": "2025-09-05",
      "open": 405.469034,
      "high": 446.015937,
      "low": 405.469034,
      "close": 446.015937,
      "volume": 590806.0
    },
    {
      "date": "2025-09-08",
      "open": 459.861222,
      "high": 489.529687,
      "low": 447.004886,
      "close": 486.562841,
      "volume": 602877.0
    },
    {
      "date": "2025-09-09",
      "open": 486.562841,
      "high": 499.419176,
      "low": 476.673352,
      "close": 484.584943,
      "volume": 353557.0
    },
    {
      "date": "2025-09-10",
      "open": 492.496534,
      "high": 492.496534,
      "low": 447.499361,
      "close": 449.477259,
      "volume": 609999.0
    },
    {
      "date": "2025-09-11",
      "open": 440.082244,
      "high": 449.477259,
      "low": 427.720384,
      "close": 429.203807,
      "volume": 372464.0
    },
    {
      "date": "2025-09-12",
      "open": 417.33642,
      "high": 443.049091,
      "low": 415.358523,
      "close": 435.631974,
      "volume": 274608.0
    },
    {
      "date": "2025-09-15",
      "open": 435.631974,
      "high": 435.631974,
      "low": 397.557443,
      "close": 420.303267,
      "volume": 310167.0
    },
    {
      "date": "2025-09-16",
      "open": 420.303267,
      "high": 420.303267,
      "low": 408.930355,
      "close": 414.864048,
      "volume": 118458.0
    },
    {
      "date": "2025-09-17",
      "open": 404.480085,
      "high": 428.214858,
      "low": 403.985611,
      "close": 416.841946,
      "volume": 230414.0
    },
    {
      "date": "2025-09-18",
      "open": 405.963509,
      "high": 413.875099,
      "low": 405.469034,
      "close": 407.941406,
      "volume": 120826.0
    },
    {
      "date": "2025-09-19",
      "open": 407.446932,
      "high": 434.643026,
      "low": 393.601648,
      "close": 434.643026,
      "volume": 308394.0
    },
    {
      "date": "2025-09-22",
      "open": 433.159602,
      "high": 433.159602,
      "low": 413.380625,
      "close": 413.875099,
      "volume": 146640.0
    },
    {
      "date": "2025-09-23",
      "open": 413.875099,
      "high": 421.78669,
      "low": 403.985611,
      "close": 416.347472,
      "volume": 116128.0
    },
    {
      "date": "2025-09-24",
      "open": 407.446932,
      "high": 411.897202,
      "low": 399.535341,
      "close": 403.491136,
      "volume": 117466.0
    },
    {
      "date": "2025-09-25",
      "open": 417.33642,
      "high": 417.33642,
      "low": 402.996662,
      "close": 403.491136,
      "volume": 58587.0
    },
    {
      "date": "2025-09-26",
      "open": 405.469034,
      "high": 405.469034,
      "low": 388.162429,
      "close": 397.557443,
      "volume": 286399.0
    },
    {
      "date": "2025-09-30",
      "open": 396.568494,
      "high": 415.358523,
      "low": 396.568494,
      "close": 404.97456,
      "volume": 95195.0
    },
    {
      "date": "2025-10-01",
      "open": 398.546392,
      "high": 403.491136,
      "low": 397.557443,
      "close": 399.040866,
      "volume": 49205.0
    },
    {
      "date": "2025-10-02",
      "open": 399.040866,
      "high": 405.469034,
      "low": 389.645852,
      "close": 399.040866,
      "volume": 51754.0
    },
    {
      "date": "2025-10-03",
      "open": 399.040866,
      "high": 399.535341,
      "low": 393.601648,
      "close": 399.040866,
      "volume": 46549.0
    },
    {
      "date": "2025-10-07",
      "open": 404.97456,
      "high": 404.97456,
      "low": 389.645852,
      "close": 395.579545,
      "volume": 141202.0
    },
    {
      "date": "2025-10-08",
      "open": 394.096122,
      "high": 394.096122,
      "low": 379.756364,
      "close": 391.129276,
      "volume": 165134.0
    },
    {
      "date": "2025-10-09",
      "open": 391.129276,
      "high": 395.085071,
      "low": 382.72321,
      "close": 384.701108,
      "volume": 216744.0
    },
    {
      "date": "2025-10-13",
      "open": 364.922131,
      "high": 384.701108,
      "low": 364.922131,
      "close": 384.701108,
      "volume": 140066.0
    },
    {
      "date": "2025-10-14",
      "open": 377.283991,
      "high": 382.228736,
      "low": 367.888977,
      "close": 367.888977,
      "volume": 150171.0
    },
    {
      "date": "2025-10-15",
      "open": 364.922131,
      "high": 366.900028,
      "low": 341.187358,
      "close": 365.91108,
      "volume": 279749.0
    },
    {
      "date": "2025-10-16",
      "open": 359.482912,
      "high": 365.91108,
      "low": 354.043693,
      "close": 360.966335,
      "volume": 85722.0
    },
    {
      "date": "2025-10-17",
      "open": 361.955284,
      "high": 377.778466,
      "low": 351.571321,
      "close": 355.032642,
      "volume": 154736.0
    },
    {
      "date": "2025-10-20",
      "open": 349.098949,
      "high": 375.800568,
      "low": 346.132102,
      "close": 358.493963,
      "volume": 91223.0
    },
    {
      "date": "2025-10-21",
      "open": 361.955284,
      "high": 365.91108,
      "low": 352.065795,
      "close": 355.032642,
      "volume": 118983.0
    },
    {
      "date": "2025-10-22",
      "open": 354.043693,
      "high": 355.032642,
      "low": 341.681832,
      "close": 351.076847,
      "volume": 235339.0
    },
    {
      "date": "2025-10-23",
      "open": 346.132102,
      "high": 352.065795,
      "low": 345.143153,
      "close": 352.065795,
      "volume": 51737.0
    },
    {
      "date": "2025-10-27",
      "open": 351.076847,
      "high": 373.82267,
      "low": 347.615526,
      "close": 363.933182,
      "volume": 92523.0
    },
    {
      "date": "2025-10-28",
      "open": 360.966335,
      "high": 363.933182,
      "low": 354.043693,
      "close": 362.944233,
      "volume": 53936.0
    },
    {
      "date": "2025-10-29",
      "open": 362.944233,
      "high": 374.317145,
      "low": 362.944233,
      "close": 369.866875,
      "volume": 69066.0
    },
    {
      "date": "2025-10-30",
      "open": 362.944233,
      "high": 363.933182,
      "low": 356.021591,
      "close": 357.01054,
      "volume": 54239.0
    },
    {
      "date": "2025-10-31",
      "open": 355.032642,
      "high": 365.91108,
      "low": 351.076847,
      "close": 361.955284,
      "volume": 52738.0
    },
    {
      "date": "2025-11-03",
      "open": 358.988438,
      "high": 380.250838,
      "low": 358.988438,
      "close": 372.339247,
      "volume": 99229.0
    },
    {
      "date": "2025-11-04",
      "open": 372.339247,
      "high": 375.800568,
      "low": 359.482912,
      "close": 365.91108,
      "volume": 47442.0
    },
    {
      "date": "2025-11-05",
      "open": 358.493963,
      "high": 361.955284,
      "low": 351.076847,
      "close": 356.021591,
      "volume": 43539.0
    },
    {
      "date": "2025-11-06",
      "open": 356.021591,
      "high": 367.888977,
      "low": 354.043693,
      "close": 367.888977,
      "volume": 50722.0
    },
    {
      "date": "2025-11-07",
      "open": 360.966335,
      "high": 367.888977,
      "low": 360.966335,
      "close": 365.91108,
      "volume": 49550.0
    },
    {
      "date": "2025-11-10",
      "open": 358.493963,
      "high": 374.317145,
      "low": 350.087898,
      "close": 364.922131,
      "volume": 120159.0
    },
    {
      "date": "2025-11-11",
      "open": 364.922131,
      "high": 387.667955,
      "low": 363.438707,
      "close": 380.745313,
      "volume": 198428.0
    },
    {
      "date": "2025-11-12",
      "open": 380.745313,
      "high": 395.579545,
      "low": 380.250838,
      "close": 382.228736,
      "volume": 136144.0
    },
    {
      "date": "2025-11-13",
      "open": 381.239787,
      "high": 381.734261,
      "low": 374.317145,
      "close": 375.800568,
      "volume": 78417.0
    },
    {
      "date": "2025-11-14",
      "open": 371.350298,
      "high": 378.767415,
      "low": 369.866875,
      "close": 375.800568,
      "volume": 39178.0
    },
    {
      "date": "2025-11-17",
      "open": 388.656903,
      "high": 388.656903,
      "low": 365.91108,
      "close": 375.800568,
      "volume": 71285.0
    },
    {
      "date": "2025-11-18",
      "open": 373.82267,
      "high": 373.82267,
      "low": 350.582372,
      "close": 362.944233,
      "volume": 219767.0
    },
    {
      "date": "2025-11-19",
      "open": 355.527116,
      "high": 360.966335,
      "low": 347.121051,
      "close": 355.032642,
      "volume": 160023.0
    },
    {
      "date": "2025-11-20",
      "open": 357.999489,
      "high": 367.888977,
      "low": 355.032642,
      "close": 361.955284,
      "volume": 95308.0
    },
    {
      "date": "2025-11-21",
      "open": 354.043693,
      "high": 359.977386,
      "low": 350.087898,
      "close": 359.977386,
      "volume": 61103.0
    },
    {
      "date": "2025-11-24",
      "open": 360.966335,
      "high": 361.46081,
      "low": 349.098949,
      "close": 349.098949,
      "volume": 42580.0
    },
    {
      "date": "2025-11-25",
      "open": 349.593423,
      "high": 361.46081,
      "low": 349.593423,
      "close": 358.493963,
      "volume": 76695.0
    },
    {
      "date": "2025-11-26",
      "open": 350.087898,
      "high": 377.778466,
      "low": 350.087898,
      "close": 375.800568,
      "volume": 202120.0
    },
    {
      "date": "2025-11-27",
      "open": 371.844773,
      "high": 387.667955,
      "low": 371.844773,
      "close": 376.789517,
      "volume": 83347.0
    },
    {
      "date": "2025-11-28",
      "open": 375.800568,
      "high": 378.767415,
      "low": 371.844773,
      "close": 377.778466,
      "volume": 103161.0
    },
    {
      "date": "2025-12-01",
      "open": 377.283991,
      "high": 377.283991,
      "low": 369.866875,
      "close": 375.800568,
      "volume": 78322.0
    },
    {
      "date": "2025-12-02",
      "open": 370.361349,
      "high": 380.745313,
      "low": 368.383452,
      "close": 376.789517,
      "volume": 219751.0
    },
    {
      "date": "2025-12-03",
      "open": 377.778466,
      "high": 377.778466,
      "low": 371.844773,
      "close": 373.82267,
      "volume": 33026.0
    },
    {
      "date": "2025-12-04",
      "open": 373.82267,
      "high": 373.82267,
      "low": 366.900028,
      "close": 369.372401,
      "volume": 85952.0
    },
    {
      "date": "2025-12-05",
      "open": 369.372401,
      "high": 371.350298,
      "low": 360.471861,
      "close": 362.944233,
      "volume": 126528.0
    },
    {
      "date": "2025-12-08",
      "open": 356.021591,
      "high": 362.944233,
      "low": 338.220511,
      "close": 348.11,
      "volume": 358213.0
    },
    {
      "date": "2025-12-09",
      "open": 348.11,
      "high": 352.065795,
      "low": 338.220511,
      "close": 348.11,
      "volume": 196443.0
    },
    {
      "date": "2025-12-10",
      "open": 353.0,
      "high": 379.0,
      "low": 353.0,
      "close": 372.0,
      "volume": 174300.0
    },
    {
      "date": "2025-12-11",
      "open": 384.5,
      "high": 384.5,
      "low": 372.5,
      "close": 377.0,
      "volume": 82127.0
    },
    {
      "date": "2025-12-12",
      "open": 380.0,
      "high": 389.0,
      "low": 373.5,
      "close": 385.0,
      "volume": 212377.0
    },
    {
      "date": "2025-12-15",
      "open": 375.0,
      "high": 398.0,
      "low": 375.0,
      "close": 398.0,
      "volume": 204092.0
    },
    {
      "date": "2025-12-16",
      "open": 396.5,
      "high": 396.5,
      "low": 370.5,
      "close": 382.0,
      "volume": 192951.0
    },
    {
      "date": "2025-12-17",
      "open": 382.0,
      "high": 388.0,
      "low": 379.0,
      "close": 381.0,
      "volume": 102030.0
    },
    {
      "date": "2025-12-18",
      "open": 377.5,
      "high": 381.0,
      "low": 370.0,
      "close": 373.0,
      "volume": 116746.0
    },
    {
      "date": "2025-12-19",
      "open": 369.5,
      "high": 370.0,
      "low": 360.0,
      "close": 360.0,
      "volume": 126320.0
    },
    {
      "date": "2025-12-22",
      "open": 363.0,
      "high": 366.0,
      "low": 349.0,
      "close": 354.5,
      "volume": 136973.0
    },
    {
      "date": "2025-12-23",
      "open": 359.5,
      "high": 361.5,
      "low": 352.5,
      "close": 355.0,
      "volume": 82285.0
    },
    {
      "date": "2025-12-24",
      "open": 357.0,
      "high": 368.0,
      "low": 355.0,
      "close": 359.0,
      "volume": 228138.0
    },
    {
      "date": "2025-12-26",
      "open": 358.0,
      "high": 365.0,
      "low": 353.0,
      "close": 359.0,
      "volume": 106428.0
    },
    {
      "date": "2025-12-29",
      "open": 359.0,
      "high": 361.5,
      "low": 343.5,
      "close": 351.5,
      "volume": 153704.0
    },
    {
      "date": "2025-12-30",
      "open": 346.5,
      "high": 351.5,
      "low": 337.0,
      "close": 343.5,
      "volume": 226720.0
    },
    {
      "date": "2025-12-31",
      "open": 343.5,
      "high": 347.5,
      "low": 342.5,
      "close": 342.5,
      "volume": 44280.0
    },
    {
      "date": "2026-01-02",
      "open": 342.5,
      "high": 345.0,
      "low": 308.5,
      "close": 308.5,
      "volume": 479768.0
    },
    {
      "date": "2026-01-05",
      "open": 320.0,
      "high": 333.0,
      "low": 315.0,
      "close": 317.0,
      "volume": 280029.0
    },
    {
      "date": "2026-01-06",
      "open": 317.0,
      "high": 322.0,
      "low": 314.5,
      "close": 319.0,
      "volume": 212393.0
    },
    {
      "date": "2026-01-07",
      "open": 318.0,
      "high": 336.0,
      "low": 318.0,
      "close": 326.5,
      "volume": 163054.0
    },
    {
      "date": "2026-01-08",
      "open": 332.5,
      "high": 346.5,
      "low": 325.0,
      "close": 336.5,
      "volume": 246165.0
    },
    {
      "date": "2026-01-09",
      "open": 336.0,
      "high": 341.5,
      "low": 330.0,
      "close": 333.5,
      "volume": 73310.0
    },
    {
      "date": "2026-01-12",
      "open": 332.0,
      "high": 336.0,
      "low": 327.0,
      "close": 327.0,
      "volume": 83453.0
    },
    {
      "date": "2026-01-13",
      "open": 317.0,
      "high": 348.0,
      "low": 315.5,
      "close": 332.5,
      "volume": 679555.0
    },
    {
      "date": "2026-01-14",
      "open": 331.5,
      "high": 338.0,
      "low": 327.0,
      "close": 338.0,
      "volume": 215607.0
    },
    {
      "date": "2026-01-15",
      "open": 338.0,
      "high": 359.0,
      "low": 337.5,
      "close": 351.0,
      "volume": 273382.0
    },
    {
      "date": "2026-01-16",
      "open": 352.5,
      "high": 363.0,
      "low": 352.5,
      "close": 360.0,
      "volume": 175460.0
    },
    {
      "date": "2026-01-19",
      "open": 359.5,
      "high": 385.0,
      "low": 359.5,
      "close": 379.5,
      "volume": 433924.0
    },
    {
      "date": "2026-01-20",
      "open": 380.0,
      "high": 417.0,
      "low": 380.0,
      "close": 415.5,
      "volume": 610436.0
    },
    {
      "date": "2026-01-21",
      "open": 429.5,
      "high": 445.0,
      "low": 429.5,
      "close": 433.0,
      "volume": 538552.0
    },
    {
      "date": "2026-01-22",
      "open": 437.5,
      "high": 457.5,
      "low": 437.5,
      "close": 443.0,
      "volume": 337418.0
    },
    {
      "date": "2026-01-23",
      "open": 444.0,
      "high": 449.0,
      "low": 426.0,
      "close": 430.0,
      "volume": 319543.0
    },
    {
      "date": "2026-01-26",
      "open": 435.5,
      "high": 473.0,
      "low": 426.0,
      "close": 473.0,
      "volume": 578263.0
    },
    {
      "date": "2026-01-27",
      "open": 490.0,
      "high": 520.0,
      "low": 489.5,
      "close": 513.0,
      "volume": 637182.0
    },
    {
      "date": "2026-01-28",
      "open": 520.0,
      "high": 563.0,
      "low": 515.0,
      "close": 560.0,
      "volume": 582931.0
    },
    {
      "date": "2026-01-29",
      "open": 590.0,
      "high": 610.0,
      "low": 561.0,
      "close": 585.0,
      "volume": 243685.0
    },
    {
      "date": "2026-01-30",
      "open": 590.0,
      "high": 600.0,
      "low": 562.0,
      "close": 600.0,
      "volume": 190481.0
    },
    {
      "date": "2026-02-02",
      "open": 588.0,
      "high": 620.0,
      "low": 585.0,
      "close": 601.0,
      "volume": 400758.0
    },
    {
      "date": "2026-02-03",
      "open": 615.0,
      "high": 615.0,
      "low": 587.0,
      "close": 589.0,
      "volume": 83247.0
    },
    {
      "date": "2026-02-04",
      "open": 589.0,
      "high": 620.0,
      "low": 589.0,
      "close": 620.0,
      "volume": 130868.0
    },
    {
      "date": "2026-02-05",
      "open": 620.0,
      "high": 653.0,
      "low": 620.0,
      "close": 648.0,
      "volume": 121617.0
    },
    {
      "date": "2026-02-06",
      "open": 648.0,
      "high": 679.0,
      "low": 648.0,
      "close": 679.0,
      "volume": 156413.0
    },
    {
      "date": "2026-02-09",
      "open": 695.0,
      "high": 698.0,
      "low": 685.0,
      "close": 685.0,
      "volume": 106632.0
    },
    {
      "date": "2026-02-10",
      "open": 660.0,
      "high": 695.0,
      "low": 660.0,
      "close": 688.0,
      "volume": 67895.0
    },
    {
      "date": "2026-02-11",
      "open": 688.0,
      "high": 688.0,
      "low": 662.0,
      "close": 678.0,
      "volume": 82606.0
    },
    {
      "date": "2026-02-23",
      "open": 651.0,
      "high": 680.0,
      "low": 650.0,
      "close": 660.0,
      "volume": 118525.0
    },
    {
      "date": "2026-02-24",
      "open": 660.0,
      "high": 690.0,
      "low": 655.0,
      "close": 690.0,
      "volume": 74873.0
    },
    {
      "date": "2026-02-25",
      "open": 690.0,
      "high": 700.0,
      "low": 680.0,
      "close": 690.0,
      "volume": 60188.0
    },
    {
      "date": "2026-02-26",
      "open": 715.0,
      "high": 758.0,
      "low": 621.0,
      "close": 695.0,
      "volume": 644568.0
    },
    {
      "date": "2026-03-02",
      "open": 694.0,
      "high": 718.0,
      "low": 665.0,
      "close": 690.0,
      "volume": 401880.0
    },
    {
      "date": "2026-03-03",
      "open": 690.0,
      "high": 694.0,
      "low": 630.0,
      "close": 638.0,
      "volume": 882629.0
    },
    {
      "date": "2026-03-04",
      "open": 622.0,
      "high": 632.0,
      "low": 602.0,
      "close": 613.0,
      "volume": 425198.0
    },
    {
      "date": "2026-03-05",
      "open": 617.0,
      "high": 648.0,
      "low": 585.0,
      "close": 591.0,
      "volume": 480721.0
    },
    {
      "date": "2026-03-06",
      "open": 570.0,
      "high": 595.0,
      "low": 545.0,
      "close": 564.0,
      "volume": 464179.0
    },
    {
      "date": "2026-03-09",
      "open": 508.0,
      "high": 560.0,
      "low": 508.0,
      "close": 560.0,
      "volume": 301069.0
    },
    {
      "date": "2026-03-10",
      "open": 586.0,
      "high": 605.0,
      "low": 558.0,
      "close": 575.0,
      "volume": 294798.0
    },
    {
      "date": "2026-03-11",
      "open": 575.0,
      "high": 610.0,
      "low": 570.0,
      "close": 599.0,
      "volume": 147283.0
    },
    {
      "date": "2026-03-12",
      "open": 599.0,
      "high": 603.0,
      "low": 563.0,
      "close": 577.0,
      "volume": 194281.0
    },
    {
      "date": "2026-03-13",
      "open": 562.0,
      "high": 579.0,
      "low": 557.0,
      "close": 574.0,
      "volume": 152514.0
    },
    {
      "date": "2026-03-16",
      "open": 567.0,
      "high": 584.0,
      "low": 563.0,
      "close": 565.0,
      "volume": 122322.0
    },
    {
      "date": "2026-03-17",
      "open": 565.0,
      "high": 585.0,
      "low": 556.0,
      "close": 562.0,
      "volume": 143909.0
    },
    {
      "date": "2026-03-18",
      "open": 560.0,
      "high": 593.0,
      "low": 560.0,
      "close": 583.0,
      "volume": 178343.0
    },
    {
      "date": "2026-03-19",
      "open": 573.0,
      "high": 589.0,
      "low": 565.0,
      "close": 583.0,
      "volume": 152924.0
    },
    {
      "date": "2026-03-20",
      "open": 581.0,
      "high": 584.0,
      "low": 557.0,
      "close": 569.0,
      "volume": 224449.0
    },
    {
      "date": "2026-03-23",
      "open": 541.0,
      "high": 575.0,
      "low": 541.0,
      "close": 545.0,
      "volume": 227700.0
    },
    {
      "date": "2026-03-24",
      "open": 545.0,
      "high": 562.0,
      "low": 509.0,
      "close": 525.0,
      "volume": 404906.0
    },
    {
      "date": "2026-03-25",
      "open": 565.0,
      "high": 568.0,
      "low": 527.0,
      "close": 568.0,
      "volume": 142625.0
    },
    {
      "date": "2026-03-26",
      "open": 570.0,
      "high": 589.0,
      "low": 567.0,
      "close": 579.0,
      "volume": 178861.0
    },
    {
      "date": "2026-03-27",
      "open": 579.0,
      "high": 584.0,
      "low": 563.0,
      "close": 567.0,
      "volume": 108511.0
    },
    {
      "date": "2026-03-30",
      "open": 550.0,
      "high": 573.0,
      "low": 549.0,
      "close": 570.0,
      "volume": 80409.0
    },
    {
      "date": "2026-03-31",
      "open": 572.0,
      "high": 572.0,
      "low": 548.0,
      "close": 561.0,
      "volume": 187139.0
    },
    {
      "date": "2026-04-01",
      "open": 560.0,
      "high": 587.0,
      "low": 560.0,
      "close": 570.0,
      "volume": 133258.0
    },
    {
      "date": "2026-04-02",
      "open": 578.0,
      "high": 578.0,
      "low": 556.0,
      "close": 562.0,
      "volume": 103713.0
    },
    {
      "date": "2026-04-07",
      "open": 566.0,
      "high": 606.0,
      "low": 562.0,
      "close": 592.0,
      "volume": 183421.0
    },
    {
      "date": "2026-04-08",
      "open": 592.0,
      "high": 608.0,
      "low": 585.0,
      "close": 608.0,
      "volume": 195396.0
    },
    {
      "date": "2026-04-09",
      "open": 609.0,
      "high": 628.0,
      "low": 602.0,
      "close": 623.0,
      "volume": 171213.0
    },
    {
      "date": "2026-04-10",
      "open": 634.0,
      "high": 671.0,
      "low": 633.0,
      "close": 647.0,
      "volume": 340566.0
    },
    {
      "date": "2026-04-13",
      "open": 676.0,
      "high": 711.0,
      "low": 661.0,
      "close": 711.0,
      "volume": 453187.0
    },
    {
      "date": "2026-04-14",
      "open": 735.0,
      "high": 782.0,
      "low": 709.0,
      "close": 782.0,
      "volume": 613278.0
    },
    {
      "date": "2026-04-15",
      "open": 810.0,
      "high": 828.0,
      "low": 763.0,
      "close": 775.0,
      "volume": 477289.0
    },
    {
      "date": "2026-04-16",
      "open": 767.0,
      "high": 800.0,
      "low": 760.0,
      "close": 780.0,
      "volume": 202180.0
    },
    {
      "date": "2026-04-17",
      "open": 767.0,
      "high": 799.0,
      "low": 761.0,
      "close": 770.0,
      "volume": 71355.0
    },
    {
      "date": "2026-04-20",
      "open": 775.0,
      "high": 800.0,
      "low": 775.0,
      "close": 800.0,
      "volume": 70892.0
    },
    {
      "date": "2026-04-21",
      "open": 804.0,
      "high": 804.0,
      "low": 790.0,
      "close": 798.0,
      "volume": 83023.0
    },
    {
      "date": "2026-04-22",
      "open": 808.0,
      "high": 860.0,
      "low": 791.0,
      "close": 860.0,
      "volume": 128102.0
    },
    {
      "date": "2026-04-23",
      "open": 929.0,
      "high": 929.0,
      "low": 801.0,
      "close": 865.0,
      "volume": 176633.0
    },
    {
      "date": "2026-04-24",
      "open": 925.0,
      "high": 925.0,
      "low": 840.0,
      "close": 840.0,
      "volume": 114184.0
    },
    {
      "date": "2026-04-27",
      "open": 839.0,
      "high": 839.0,
      "low": 756.0,
      "close": 756.0,
      "volume": 252866.0
    },
    {
      "date": "2026-04-28",
      "open": 756.0,
      "high": 786.0,
      "low": 756.0,
      "close": 766.0,
      "volume": 71404.0
    },
    {
      "date": "2026-04-29",
      "open": 780.0,
      "high": 817.0,
      "low": 771.0,
      "close": 787.0,
      "volume": 94868.0
    },
    {
      "date": "2026-04-30",
      "open": 778.0,
      "high": 792.0,
      "low": 771.0,
      "close": 771.0,
      "volume": 74557.0
    },
    {
      "date": "2026-05-04",
      "open": 764.0,
      "high": 805.0,
      "low": 731.0,
      "close": 758.0,
      "volume": 368017.0
    },
    {
      "date": "2026-05-05",
      "open": 790.0,
      "high": 810.0,
      "low": 684.0,
      "close": 779.0,
      "volume": 836279.0
    },
    {
      "date": "2026-05-06",
      "open": 856.0,
      "high": 856.0,
      "low": 702.0,
      "close": 702.0,
      "volume": 753474.0
    },
    {
      "date": "2026-05-07",
      "open": 686.0,
      "high": 706.0,
      "low": 670.0,
      "close": 684.0,
      "volume": 309753.0
    },
    {
      "date": "2026-05-08",
      "open": 684.0,
      "high": 709.0,
      "low": 660.0,
      "close": 690.0,
      "volume": 186257.0
    },
    {
      "date": "2026-05-11",
      "open": 685.0,
      "high": 695.0,
      "low": 665.0,
      "close": 687.0,
      "volume": 144225.0
    },
    {
      "date": "2026-05-12",
      "open": 699.0,
      "high": 699.0,
      "low": 660.0,
      "close": 680.0,
      "volume": 211712.0
    },
    {
      "date": "2026-05-13",
      "open": 675.0,
      "high": 679.0,
      "low": 666.0,
      "close": 678.0,
      "volume": 57062.0
    },
    {
      "date": "2026-05-14",
      "open": 692.0,
      "high": 745.0,
      "low": 677.0,
      "close": 716.0,
      "volume": 321683.0
    },
    {
      "date": "2026-05-15",
      "open": 715.0,
      "high": 723.0,
      "low": 682.0,
      "close": 687.0,
      "volume": 126131.0
    },
    {
      "date": "2026-05-18",
      "open": 671.0,
      "high": 690.0,
      "low": 666.0,
      "close": 672.0,
      "volume": 97330.0
    },
    {
      "date": "2026-05-19",
      "open": 683.0,
      "high": 683.0,
      "low": 654.0,
      "close": 669.0,
      "volume": 111443.0
    },
    {
      "date": "2026-05-20",
      "open": 668.0,
      "high": 688.0,
      "low": 662.0,
      "close": 687.0,
      "volume": 55505.0
    },
    {
      "date": "2026-05-21",
      "open": 702.0,
      "high": 710.0,
      "low": 674.0,
      "close": 674.0,
      "volume": 86143.0
    },
    {
      "date": "2026-05-22",
      "open": 674.0,
      "high": 685.0,
      "low": 669.0,
      "close": 669.0,
      "volume": 94907.0
    },
    {
      "date": "2026-05-25",
      "open": 678.0,
      "high": 679.0,
      "low": 648.0,
      "close": 656.0,
      "volume": 161051.0
    },
    {
      "date": "2026-05-26",
      "open": 657.0,
      "high": 670.0,
      "low": 649.0,
      "close": 668.0,
      "volume": 65765.0
    },
    {
      "date": "2026-05-27",
      "open": 704.0,
      "high": 717.0,
      "low": 680.0,
      "close": 714.0,
      "volume": 248961.0
    },
    {
      "date": "2026-05-28",
      "open": 704.0,
      "high": 757.0,
      "low": 668.0,
      "close": 668.0,
      "volume": 320980.0
    },
    {
      "date": "2026-05-29",
      "open": 675.0,
      "high": 675.0,
      "low": 643.0,
      "close": 645.0,
      "volume": 235781.0
    },
    {
      "date": "2026-06-01",
      "open": 667.0,
      "high": 667.0,
      "low": 607.0,
      "close": 644.0,
      "volume": 291654.0
    },
    {
      "date": "2026-06-02",
      "open": 659.0,
      "high": 659.0,
      "low": 626.0,
      "close": 631.0,
      "volume": 75749.0
    },
    {
      "date": "2026-06-03",
      "open": 634.0,
      "high": 636.0,
      "low": 623.0,
      "close": 635.0,
      "volume": 52113.0
    },
    {
      "date": "2026-06-04",
      "open": 629.0,
      "high": 650.0,
      "low": 625.0,
      "close": 645.0,
      "volume": 52439.0
    },
    {
      "date": "2026-06-05",
      "open": 645.0,
      "high": 682.0,
      "low": 632.0,
      "close": 658.0,
      "volume": 137949.0
    },
    {
      "date": "2026-06-08",
      "open": 610.0,
      "high": 694.0,
      "low": 610.0,
      "close": 677.0,
      "volume": 254728.0
    },
    {
      "date": "2026-06-09",
      "open": 677.0,
      "high": 709.0,
      "low": 677.0,
      "close": 704.0,
      "volume": 211881.0
    },
    {
      "date": "2026-06-10",
      "open": 709.0,
      "high": 747.0,
      "low": 709.0,
      "close": 725.0,
      "volume": 314118.0
    },
    {
      "date": "2026-06-11",
      "open": 732.0,
      "high": 735.0,
      "low": 700.0,
      "close": 704.0,
      "volume": 324264.0
    },
    {
      "date": "2026-06-12",
      "open": 707.0,
      "high": 728.0,
      "low": 707.0,
      "close": 717.0,
      "volume": 138748.0
    },
    {
      "date": "2026-06-15",
      "open": 733.0,
      "high": 746.0,
      "low": 705.0,
      "close": 740.0,
      "volume": 341664.0
    },
    {
      "date": "2026-06-16",
      "open": 748.0,
      "high": 814.0,
      "low": 743.0,
      "close": 814.0,
      "volume": 462456.0
    },
    {
      "date": "2026-06-17",
      "open": 870.0,
      "high": 895.0,
      "low": 852.0,
      "close": 895.0,
      "volume": 303249.0
    },
    {
      "date": "2026-06-18",
      "open": 938.0,
      "high": 968.0,
      "low": 895.0,
      "close": 911.0,
      "volume": 740735.0
    },
    {
      "date": "2026-06-23",
      "open": 887.0,
      "high": 889.0,
      "low": 819.0,
      "close": 833.0,
      "volume": 228301.0
    },
    {
      "date": "2026-06-24",
      "open": 834.0,
      "high": 860.0,
      "low": 809.0,
      "close": 860.0,
      "volume": 172420.0
    },
    {
      "date": "2026-06-25",
      "open": 870.0,
      "high": 900.0,
      "low": 845.0,
      "close": 879.0,
      "volume": 190032.0
    },
    {
      "date": "2026-06-26",
      "open": 870.0,
      "high": 875.0,
      "low": 840.0,
      "close": 862.0,
      "volume": 146455.0
    },
    {
      "date": "2026-06-29",
      "open": 861.0,
      "high": 888.0,
      "low": 847.0,
      "close": 856.0,
      "volume": 139411.0
    },
    {
      "date": "2026-06-30",
      "open": 870.0,
      "high": 882.0,
      "low": 854.0,
      "close": 871.0,
      "volume": 125762.0
    }
  ]
}